MANIFEST.in
setup.cfg
setup.py
stratus_api/tasks/__init__.py
stratus_api/tasks/base.py
stratus_api/tasks/tasks/__init__.py
stratus_api/tasks/tasks/sample.py
stratus_api_tasks.egg-info/PKG-INFO
stratus_api_tasks.egg-info/SOURCES.txt
stratus_api_tasks.egg-info/dependency_links.txt
stratus_api_tasks.egg-info/requires.txt
stratus_api_tasks.egg-info/top_level.txt