Metadata-Version: 2.1
Name: stratus-api-tasks
Version: 0.0.9
Summary: Streamlined Celery Task
Home-page: https://bitbucket.org/adarainc/stratus-api-tasks
Author: DOT
Author-email: dot@adara.com
Classifier: Programming Language :: Python :: 3
Classifier: License :: OSI Approved :: MIT License
Classifier: Operating System :: OS Independent
Requires-Python: >=3.11
